teedoc_plugin_baidu_tongji/__init__.py
teedoc_plugin_baidu_tongji/assets/main.js
teedoc_plugin_baidu_tongji-1.0.4.dist-info/LICENSE
teedoc_plugin_baidu_tongji-1.0.4.dist-info/METADATA
teedoc_plugin_baidu_tongji-1.0.4.dist-info/WHEEL
teedoc_plugin_baidu_tongji-1.0.4.dist-info/top_level.txt
teedoc_plugin_baidu_tongji-1.0.4.dist-info/RECORD
