Metadata-Version: 2.1
Name: teedoc-plugin-baidu-tongji
Version: 1.0.4
Summary: baidu tongji plugin for teedoc
Home-page: https://github.com/Neutree/teedoc
Author: Neucrack
Author-email: CZD666666@gmail.com
License: MIT
Keywords: baidu tongji doc website markdown jupyter notbook generator teedoc search plugin
Platform: UNKNOWN
Classifier: Intended Audience :: Developers
Classifier: License :: OSI Approved :: MIT License
Classifier: Programming Language :: Python :: 3
